cryoblob/.ipynb_checkpoints/__init__-checkpoint.py
cryoblob/.ipynb_checkpoints/blob_detection-checkpoint.py
cryoblob/.ipynb_checkpoints/files-checkpoint.py
cryoblob/.ipynb_checkpoints/plots-checkpoint.py
cryoblob/.ipynb_checkpoints/types-checkpoint.py
cryoblob/.ipynb_checkpoints/utilities-checkpoint.py
cryoblob/__init__.py
cryoblob/adapt.py
cryoblob/blobs.py
cryoblob/files.py
cryoblob/image.py
cryoblob/multi.py
cryoblob/params/organization.json
cryoblob/plots.py
cryoblob/py.typed
cryoblob/types.py
cryoblob/valid.py
cryoblob-2025.8.2.dist-info/WHEEL
cryoblob-2025.8.2.dist-info/METADATA
cryoblob-2025.8.2.dist-info/RECORD
