Metadata-Version: 2.4
Name: cryoblob
Version: 2025.8.2
Summary: Particle Picking of Cryo-EM Datasets
Keywords: electron microscopy,cryoEM,image processing,JAX,blob detection
Author: Debangshu Mukherjee, Alexis N. Williams, Spenser R. Cox, Marshall T. McDonnell, Albina Y. Borisevich
Author-email: Debangshu Mukherjee <mukherjeed@ornl.gov>, Alexis N. Williams <williamsan@ornl.gov>, Spenser R. Cox <coxsr@ornl.gov>, Marshall T. McDonnell <mcdonnellmt@ornl.gov>, Albina Y. Borisevich <albinab@ornl.gov>
License-Expression: MIT
Classifier: Programming Language :: Python :: 3
Classifier: Programming Language :: Python :: 3.12
Classifier: Programming Language :: Python :: 3.13
Classifier: Operating System :: OS Independent
Classifier: Typing :: Typed
Classifier: Topic :: Scientific/Engineering :: Image Processing
Requires-Dist: mrcfile==1.5.0
Requires-Dist: numpy>=1.13.0
Requires-Dist: matplotlib>=2.2.0
Requires-Dist: matplotlib-scalebar>=0.5.0
Requires-Dist: jaxtyping>=0.2.33,<0.3
Requires-Dist: beartype
Requires-Dist: pandas>=2.2.3
Requires-Dist: tqdm>=4.66.0
Requires-Dist: jax[cuda12]>=0.4.30 ; sys_platform == 'linux'
Requires-Dist: jax>=0.4.30 ; sys_platform == 'win64'
Requires-Dist: cryoblob[docs,test,dev,notebooks] ; extra == 'all'
Requires-Dist: cryoblob[docs,test] ; extra == 'dev'
Requires-Dist: black[jupyter]>=25.1.0 ; extra == 'dev'
Requires-Dist: build>=1.2.2.post1 ; extra == 'dev'
Requires-Dist: twine>=6.1.0 ; extra == 'dev'
Requires-Dist: ipywidgets>=8.1.0 ; extra == 'dev'
Requires-Dist: ruff>=0.12.9 ; extra == 'dev'
Requires-Dist: sphinx>=7.0.0 ; extra == 'docs'
Requires-Dist: sphinx-rtd-theme>=3.0.2 ; extra == 'docs'
Requires-Dist: nbsphinx>=0.9.7 ; extra == 'docs'
Requires-Dist: myst-parser>=2.0.0 ; extra == 'docs'
Requires-Dist: ipykernel>=6.29.5 ; extra == 'docs'
Requires-Dist: nbconvert>=7.16.6 ; extra == 'docs'
Requires-Dist: sphinx-autobuild>=2024.10.3 ; extra == 'docs'
Requires-Dist: furo>=2025.7.19 ; extra == 'docs'
Requires-Dist: ipywidgets>=8.1.0 ; extra == 'notebooks'
Requires-Dist: ipykernel>=6.29.5 ; extra == 'notebooks'
Requires-Dist: nbconvert>=7.16.6 ; extra == 'notebooks'
Requires-Dist: pytest>=8.3.5 ; extra == 'test'
Requires-Dist: pytest-cov>=4.0.0 ; extra == 'test'
Requires-Dist: pytest-xdist>=3.0.0 ; extra == 'test'
Requires-Dist: chex>=0.1.89 ; extra == 'test'
Maintainer: Debangshu Mukherjee
Maintainer-email: Debangshu Mukherjee <mukherjeed@ornl.gov>
Requires-Python: >=3.12
Project-URL: Documentation, https://cryoblob.readthedocs.io/
Project-URL: Homepage, https://github.com/debangshu-mukherjee/cryoblob/
Project-URL: Issues, https://github.com/debangshu-mukherjee/cryoblob/issues
Project-URL: Repository, https://github.com/debangshu-mukherjee/cryoblob/
Provides-Extra: all
Provides-Extra: dev
Provides-Extra: docs
Provides-Extra: notebooks
Provides-Extra: test
